MANIFEST.in
README.rst
requirements.txt
setup.cfg
setup.py
devutils/__init__.py
devutils/admin.py
devutils/apps.py
devutils/models.py
devutils/tests.py
devutils/utils.py
devutils/management/__init__.py
devutils/management/commands/__init__.py
devutils/management/commands/ci-cd.py
devutils/management/commands/clean.py
devutils/management/commands/cleanmigrations.py
devutils/management/commands/i18n.py
devutils/management/commands/transifex.py
django_devutils.egg-info/PKG-INFO
django_devutils.egg-info/SOURCES.txt
django_devutils.egg-info/dependency_links.txt
django_devutils.egg-info/entry_points.txt
django_devutils.egg-info/requires.txt
django_devutils.egg-info/top_level.txt