Metadata-Version: 1.1
Name: django-devutils
Version: 0.11.0
Summary: Django Development Utilities, BaseModels, BaseAdmins
Home-page: https://github.com/astrotech/django-devutils
Author: Matt Harasymczuk
Author-email: django-devutils@astrotech.io
License: MIT
Keywords: dajngo devutils development utils dev
Platform: UNKNOWN
Classifier: Development Status :: 4 - Beta
Classifier: Intended Audience :: Developers
Classifier: License :: OSI Approved :: MIT License
Classifier: Programming Language :: Python :: 3.6
